pycefsharp/__init__.py
pycefsharp/__main__.py
pycefsharp/cef.ico
pycefsharp/cef.py
pycefsharp/cli.py
pycefsharp/cefsharp/CefSharp.BrowserSubprocess.Core.dll
pycefsharp/cefsharp/CefSharp.BrowserSubprocess.exe
pycefsharp/cefsharp/CefSharp.Core.dll
pycefsharp/cefsharp/CefSharp.WinForms.dll
pycefsharp/cefsharp/CefSharp.dll
pycefsharp/cefsharp/__init__.py
pycefsharp/cefsharp/cef.pak
pycefsharp/cefsharp/cef_100_percent.pak
pycefsharp/cefsharp/cef_200_percent.pak
pycefsharp/cefsharp/cef_extensions.pak
pycefsharp/cefsharp/chrome_elf.dll
pycefsharp/cefsharp/d3dcompiler_47.dll
pycefsharp/cefsharp/devtools_resources.pak
pycefsharp/cefsharp/icudtl.dat
pycefsharp/cefsharp/libEGL.dll
pycefsharp/cefsharp/libGLESv2.dll
pycefsharp/cefsharp/libcef.dll
pycefsharp/cefsharp/snapshot_blob.bin
pycefsharp/cefsharp/v8_context_snapshot.bin
pycefsharp/cefsharp/locales/am.pak
pycefsharp/cefsharp/locales/ar.pak
pycefsharp/cefsharp/locales/bg.pak
pycefsharp/cefsharp/locales/bn.pak
pycefsharp/cefsharp/locales/ca.pak
pycefsharp/cefsharp/locales/cs.pak
pycefsharp/cefsharp/locales/da.pak
pycefsharp/cefsharp/locales/de.pak
pycefsharp/cefsharp/locales/el.pak
pycefsharp/cefsharp/locales/en-GB.pak
pycefsharp/cefsharp/locales/en-US.pak
pycefsharp/cefsharp/locales/es-419.pak
pycefsharp/cefsharp/locales/es.pak
pycefsharp/cefsharp/locales/et.pak
pycefsharp/cefsharp/locales/fa.pak
pycefsharp/cefsharp/locales/fi.pak
pycefsharp/cefsharp/locales/fil.pak
pycefsharp/cefsharp/locales/fr.pak
pycefsharp/cefsharp/locales/gu.pak
pycefsharp/cefsharp/locales/he.pak
pycefsharp/cefsharp/locales/hi.pak
pycefsharp/cefsharp/locales/hr.pak
pycefsharp/cefsharp/locales/hu.pak
pycefsharp/cefsharp/locales/id.pak
pycefsharp/cefsharp/locales/it.pak
pycefsharp/cefsharp/locales/ja.pak
pycefsharp/cefsharp/locales/kn.pak
pycefsharp/cefsharp/locales/ko.pak
pycefsharp/cefsharp/locales/lt.pak
pycefsharp/cefsharp/locales/lv.pak
pycefsharp/cefsharp/locales/ml.pak
pycefsharp/cefsharp/locales/mr.pak
pycefsharp/cefsharp/locales/ms.pak
pycefsharp-0.2.1.post4.dist-info/LICENSE
pycefsharp-0.2.1.post4.dist-info/METADATA
pycefsharp-0.2.1.post4.dist-info/WHEEL
pycefsharp-0.2.1.post4.dist-info/entry_points.txt
pycefsharp-0.2.1.post4.dist-info/top_level.txt
pycefsharp-0.2.1.post4.dist-info/RECORD
