Metadata-Version: 2.1
Name: pycefsharp
Version: 0.2.1.post4
Summary: python binding for CefSharp
Home-page: https://github.com/eseunghwan/pycefsharp
Author: eseunghwan
Author-email: shlee0920@naver.com
License: MIT license
Keywords: pythonnet,cef
Platform: UNKNOWN
Classifier: Development Status :: 3 - Alpha
Classifier: Environment :: Win32 (MS Windows)
Classifier: License :: OSI Approved :: MIT License
Classifier: Natural Language :: English
Classifier: Programming Language :: Python :: 3
Requires-Python: >=3.7
Requires-Dist: pythonnet
